ypywidgets_textual/__init__.py
ypywidgets_textual/_driver.py
ypywidgets_textual/button.py
ypywidgets_textual/plotext.py
ypywidgets_textual/switch.py
ypywidgets_textual/widget.py
ypywidgets_textual/txl/button.py
ypywidgets_textual/txl/plotext.py
ypywidgets_textual/txl/switch.py
ypywidgets_textual/txl/widget.py
ypywidgets_textual-0.5.5.dist-info/METADATA
ypywidgets_textual-0.5.5.dist-info/WHEEL
ypywidgets_textual-0.5.5.dist-info/entry_points.txt
ypywidgets_textual-0.5.5.dist-info/licenses/LICENSE
ypywidgets_textual-0.5.5.dist-info/RECORD
