Metadata-Version: 2.4
Name: ypywidgets-textual
Version: 0.5.5
Summary: Textual widgets for ypywidgets
Project-URL: Homepage, https://github.com/davidbrochart/ypywidgets-textual
Author-email: David Brochart <david.brochart@gmail.com>
License-Expression: MIT
License-File: LICENSE
Keywords: jupyter,textual,widgets,ypy
Requires-Python: >=3.8
Requires-Dist: pyte
Requires-Dist: textual-plotext
Requires-Dist: textual>=6.8.0
Requires-Dist: ypywidgets<0.10.0,>=0.9.0
